twodo_domain/__init__.py
twodo_domain/person.py
twodo_domain/todo.py
twodo_domain-0.0.2.dist-info/LICENSE
twodo_domain-0.0.2.dist-info/WHEEL
twodo_domain-0.0.2.dist-info/METADATA
twodo_domain-0.0.2.dist-info/RECORD
