Metadata-Version: 2.1
Name: twodo-domain
Version: 0.0.2
Summary: The domain (entities) of the 2do app.
Home-page: https://github.com/alexandre-labs/twodo_domain
License: MIT
Keywords: packaging,2do,clean-architecture-lab
Author: Alexandre Souza
Author-email: 0x41e@protonmail.ch
Requires-Python: >=3.6,<4.0
Classifier: License :: OSI Approved :: MIT License
Classifier: Programming Language :: Python :: 3
Classifier: Programming Language :: Python :: 3.6
Classifier: Programming Language :: Python :: 3.7
Requires-Dist: dataclasses (>=0.6,<0.7)
Project-URL: Repository, https://github.com/alexandre-labs/twodo_domain
